{
  "countData": 77,
  "countUpdate": 0,
  "resultCode": 1,
  "maxServerVersion": -1,
  "maxDataVersion": 858,
  "data": [
    {
      "id": 141,
      "Active": true,
      "VersionId": 860,
      "Latitude": "49.24109500",
      "Longitude": "28.44025400",
      "FullName": "АЗС №117 05:00 - 21:30",
      "ShortName": "",
      "Address": "м. Вінниця, вул. Арабея Генерала, 3-А",
      "Region": "Вінницька",
      "LastPriceUpdateDate": "2022-06-04",
      "ServicesAsArray": [
        {
          "id": 1,
          "Title": "Магазин"
        },
        {
          "id": 2,
          "Title": "WC"
        },
        {
          "id": 3,
          "Title": "Wi-Fi"
        },
        {
          "id": 4,
          "Title": "Їжа"
        },
        {
          "id": 5,
          "Title": "Кава"
        }
      ],
      "FuelsAsArray": [
        {
          "id": 1,
          "Title": "upg DP",
          "Price": "56.00"
        },
        {
          "id": 2,
          "Title": "95 (передоплата)",
          "Price": "0.00"
        },
        {
          "id": 4,
          "Title": "Газ",
          "Price": "0.00"
        },
        {
          "id": 5,
          "Title": "ДП (передоплата)",
          "Price": "0.00"
        },
        {
          "id": 9,
          "Title": "upg 95",
          "Price": "49.00"
        }
      ]
    },
    {
      "id": 143,
      "Active": true,
      "VersionId": 866,
      "Latitude": "49.07710700",
      "Longitude": "28.05641700",
      "FullName": "АЗС №116 05:00 - 21:30",
      "ShortName": "",
      "Address": "Вінницька обл., Жмеринський р-н, Рівська с/р, а/д Житомир-Могилів-Подільський, 160 км + 355 м",
      "Region": "Вінницька",
      "LastPriceUpdateDate": "2022-06-04",
      "ServicesAsArray": [
        {
          "id": 1,
          "Title": "Магазин"
        },
        {
          "id": 2,
          "Title": "WC"
        },
        {
          "id": 3,
          "Title": "Wi-Fi"
        },
        {
          "id": 4,
          "Title": "Їжа"
        },
        {
          "id": 5,
          "Title": "Кава"
        },
        {
          "id": 6,
          "Title": "Термінал EasyPay"
        }
      ],
      "FuelsAsArray": [
        {
          "id": 1,
          "Title": "upg DP",
          "Price": "56.00"
        },
        {
          "id": 2,
          "Title": "95 (передоплата)",
          "Price": "0.00"
        },
        {
          "id": 4,
          "Title": "Газ",
          "Price": "37.00"
        },
        {
          "id": 5,
          "Title": "ДП (передоплата)",
          "Price": "0.00"
        },
        {
          "id": 9,
          "Title": "upg 95",
          "Price": "49.00"
        }
      ]
    },
    {
      "id": 147,
      "Active": true,
      "VersionId": 904,
      "Latitude": "49.23102000",
      "Longitude": "28.51925600",
      "FullName": "АЗС №121 05:00 - 21:30",
      "ShortName": "",
      "Address": "Вінницька обл., м. Вінниця, вул. Немирівське шосе, 8-А",
      "Region": "Вінницька",
      "LastPriceUpdateDate": "2022-06-04",
      "ServicesAsArray": [
        {
          "id": 1,
          "Title": "Магазин"
        },
        {
          "id": 2,
          "Title": "WC"
        },
        {
          "id": 3,
          "Title": "Wi-Fi"
        },
        {
          "id": 4,
          "Title": "Їжа"
        },
        {
          "id": 5,
          "Title": "Кава"
        },
        {
          "id": 6,
          "Title": "Термінал EasyPay"
        },
        {
          "id": 8,
          "Title": "Підкачка шин"
        },
        {
          "id": 10,
          "Title": "VIVO-cafe"
        }
      ],
      "FuelsAsArray": [
        {
          "id": 1,
          "Title": "upg DP",
          "Price": "0.00"
        },
        {
          "id": 2,
          "Title": "95 (передоплата)",
          "Price": "0.00"
        },
        {
          "id": 4,
          "Title": "Газ",
          "Price": "37.00"
        },
        {
          "id": 5,
          "Title": "ДП (передоплата)",
          "Price": "0.00"
        },
        {
          "id": 9,
          "Title": "upg 95",
          "Price": "49.00"
        }
      ]
    },
    {
      "id": 81,
      "Active": true,
      "VersionId": 766,
      "Latitude": "51.19053000",
      "Longitude": "23.81517000",
      "FullName": "АЗС №75 06:00 - 23:00",
      "ShortName": "",
      "Address": "Волинська обл., Любомльський р-н, с. Старовойтове, вул. Прикордонників, 7А",
      "Region": "Волинська",
      "LastPriceUpdateDate": "2022-06-04",
      "ServicesAsArray": [
        {
          "id": 6,
          "Title": "Термінал EasyPay"
        }
      ],
      "FuelsAsArray": [
        {
          "id": 2,
          "Title": "95 (передоплата)",
          "Price": "48.90"
        },
        {
          "id": 3,
          "Title": "92 (передоплата)",
          "Price": "0.00"
        },
        {
          "id": 4,
          "Title": "Газ",
          "Price": "0.00"
        },
        {
          "id": 5,
          "Title": "ДП (передоплата)",
          "Price": "0.00"
        }
      ]
    },
    {
      "id": 94,
      "Active": true,
      "VersionId": 780,
      "Latitude": "51.22000000",
      "Longitude": "24.70347000",
      "FullName": "АЗС №85 06:00 - 23:00",
      "ShortName": "",
      "Address": "Волинська обл., м. Ковель, вул. Сагайдачного, 5Г",
      "Region": "Волинська",
      "LastPriceUpdateDate": "2022-06-04",
      "ServicesAsArray": [],
      "FuelsAsArray": [
        {
          "id": 2,
          "Title": "95 (передоплата)",
          "Price": "0.00"
        },
        {
          "id": 5,
          "Title": "ДП (передоплата)",
          "Price": "0.00"
        },
        {
          "id": 9,
          "Title": "upg 95",
          "Price": "0.00"
        }
      ]
    },
    {
      "id": 109,
      "Active": true,
      "VersionId": 804,
      "Latitude": "51.19402000",
      "Longitude": "23.82486000",
      "FullName": "АЗС №93 06:00 - 23:00",
      "ShortName": "",
      "Address": "Волинська обл., Любомльський район, с. Старовойтове, вул. Прикордонників, 5Б",
      "Region": "Волинська",
      "LastPriceUpdateDate": "2022-06-04",
      "ServicesAsArray": [
        {
          "id": 1,
          "Title": "Магазин"
        },
        {
          "id": 2,
          "Title": "WC"
        },
        {
          "id": 3,
          "Title": "Wi-Fi"
        },
        {
          "id": 4,
          "Title": "Їжа"
        },
        {
          "id": 5,
          "Title": "Кава"
        },
        {
          "id": 6,
          "Title": "Термінал EasyPay"
        },
        {
          "id": 8,
          "Title": "Підкачка шин"
        }
      ],
      "FuelsAsArray": [
        {
          "id": 1,
          "Title": "upg DP",
          "Price": "0.00"
        },
        {
          "id": 2,
          "Title": "95 (передоплата)",
          "Price": "48.90"
        },
        {
          "id": 4,
          "Title": "Газ",
          "Price": "0.00"
        },
        {
          "id": 5,
          "Title": "ДП (передоплата)",
          "Price": "0.00"
        },
        {
          "id": 9,
          "Title": "upg 95",
          "Price": "0.00"
        }
      ]
    },
    {
      "id": 113,
      "Active": true,
      "VersionId": 812,
      "Latitude": "50.75859000",
      "Longitude": "25.28712000",
      "FullName": "АЗС №94 06:00 - 23:00",
      "ShortName": "",
      "Address": "Волинська обл., Луцький р-н, с. Зміїнець, вул. Левадна, 2Б",
      "Region": "Волинська",
      "LastPriceUpdateDate": "2022-06-04",
      "ServicesAsArray": [
        {
          "id": 1,
          "Title": "Магазин"
        },
        {
          "id": 2,
          "Title": "WC"
        },
        {
          "id": 3,
          "Title": "Wi-Fi"
        },
        {
          "id": 4,
          "Title": "Їжа"
        },
        {
          "id": 5,
          "Title": "Кава"
        },
        {
          "id": 6,
          "Title": "Термінал EasyPay"
        },
        {
          "id": 8,
          "Title": "Підкачка шин"
        }
      ],
      "FuelsAsArray": [
        {
          "id": 1,
          "Title": "upg DP",
          "Price": "0.00"
        },
        {
          "id": 2,
          "Title": "95 (передоплата)",
          "Price": "0.00"
        },
        {
          "id": 4,
          "Title": "Газ",
          "Price": "0.00"
        },
        {
          "id": 5,
          "Title": "ДП (передоплата)",
          "Price": "0.00"
        },
        {
          "id": 9,
          "Title": "upg 95",
          "Price": "0.00"
        }
      ]
    },
    {
      "id": 131,
      "Active": true,
      "VersionId": 848,
      "Latitude": "51.20201600",
      "Longitude": "24.67672700",
      "FullName": "АЗС №106 06:00 - 23:00",
      "ShortName": "",
      "Address": "Волинська обл., м. Ковель, вул. Варшавська, 1Б",
      "Region": "Волинська",
      "LastPriceUpdateDate": "2022-06-04",
      "ServicesAsArray": [
        {
          "id": 1,
          "Title": "Магазин"
        },
        {
          "id": 2,
          "Title": "WC"
        },
        {
          "id": 3,
          "Title": "Wi-Fi"
        },
        {
          "id": 4,
          "Title": "Їжа"
        },
        {
          "id": 5,
          "Title": "Кава"
        },
        {
          "id": 6,
          "Title": "Термінал EasyPay"
        },
        {
          "id": 8,
          "Title": "Підкачка шин"
        },
        {
          "id": 10,
          "Title": "VIVO-cafe"
        }
      ],
      "FuelsAsArray": [
        {
          "id": 1,
          "Title": "upg DP",
          "Price": "0.00"
        },
        {
          "id": 2,
          "Title": "95 (передоплата)",
          "Price": "0.00"
        },
        {
          "id": 4,
          "Title": "Газ",
          "Price": "0.00"
        },
        {
          "id": 5,
          "Title": "ДП (передоплата)",
          "Price": "0.00"
        },
        {
          "id": 9,
          "Title": "upg 95",
          "Price": "49.00"
        }
      ]
    },
    {
      "id": 135,
      "Active": true,
      "VersionId": 944,
      "Latitude": "50.71690900",
      "Longitude": "25.29178500",
      "FullName": "АЗС №110 06:00 - 23:00",
      "ShortName": "",
      "Address": "Волинська обл., Луцький р-н, с. Рованці, вул. Європейська, 1-А",
      "Region": "Волинська",
      "LastPriceUpdateDate": "2022-06-04",
      "ServicesAsArray": [
        {
          "id": 1,
          "Title": "Магазин"
        },
        {
          "id": 2,
          "Title": "WC"
        },
        {
          "id": 3,
          "Title": "Wi-Fi"
        },
        {
          "id": 4,
          "Title": "Їжа"
        },
        {
          "id": 5,
          "Title": "Кава"
        },
        {
          "id": 8,
          "Title": "Підкачка шин"
        },
        {
          "id": 10,
          "Title": "VIVO-cafe"
        }
      ],
      "FuelsAsArray": [
        {
          "id": 1,
          "Title": "upg DP",
          "Price": "0.00"
        },
        {
          "id": 2,
          "Title": "95 (передоплата)",
          "Price": "0.00"
        },
        {
          "id": 4,
          "Title": "Газ",
          "Price": "0.00"
        },
        {
          "id": 5,
          "Title": "ДП (передоплата)",
          "Price": "0.00"
        },
        {
          "id": 9,
          "Title": "upg 95",
          "Price": "0.00"
        }
      ]
    },
    {
      "id": 62,
      "Active": true,
      "VersionId": 736,
      "Latitude": "48.59735000",
      "Longitude": "34.58412000",
      "FullName": "АЗС №60 06:00 - 21:00",
      "ShortName": "",
      "Address": "Дніпропетровська обл., м. Кам'янське, Єлизаветівське шосе, 27",
      "Region": "Дніпропетровська",
      "LastPriceUpdateDate": "2022-06-04",
      "ServicesAsArray": [
        {
          "id": 1,
          "Title": "Магазин"
        },
        {
          "id": 2,
          "Title": "WC"
        },
        {
          "id": 5,
          "Title": "Кава"
        }
      ],
      "FuelsAsArray": [
        {
          "id": 1,
          "Title": "upg DP",
          "Price": "56.00"
        },
        {
          "id": 2,
          "Title": "95 (передоплата)",
          "Price": "0.00"
        },
        {
          "id": 4,
          "Title": "Газ",
          "Price": "37.00"
        },
        {
          "id": 5,
          "Title": "ДП (передоплата)",
          "Price": "0.00"
        },
        {
          "id": 9,
          "Title": "upg 95",
          "Price": "49.00"
        }
      ]
    },
    {
      "id": 127,
      "Active": true,
      "VersionId": 840,
      "Latitude": "48.54499900",
      "Longitude": "34.91046100",
      "FullName": "АЗС №104 08:00 - 19:00",
      "ShortName": "",
      "Address": "Дніпропетровська обл., м. Дніпро, Полтавське шосе, 617",
      "Region": "Дніпропетровська",
      "LastPriceUpdateDate": "2022-06-04",
      "ServicesAsArray": [
        {
          "id": 1,
          "Title": "Магазин"
        },
        {
          "id": 2,
          "Title": "WC"
        },
        {
          "id": 3,
          "Title": "Wi-Fi"
        },
        {
          "id": 4,
          "Title": "Їжа"
        },
        {
          "id": 5,
          "Title": "Кава"
        },
        {
          "id": 6,
          "Title": "Термінал EasyPay"
        },
        {
          "id": 8,
          "Title": "Підкачка шин"
        },
        {
          "id": 10,
          "Title": "VIVO-cafe"
        }
      ],
      "FuelsAsArray": [
        {
          "id": 1,
          "Title": "upg DP",
          "Price": "56.00"
        },
        {
          "id": 2,
          "Title": "95 (передоплата)",
          "Price": "0.00"
        },
        {
          "id": 4,
          "Title": "Газ",
          "Price": "37.00"
        },
        {
          "id": 5,
          "Title": "ДП (передоплата)",
          "Price": "0.00"
        },
        {
          "id": 9,
          "Title": "upg 95",
          "Price": "49.00"
        }
      ]
    },
    {
      "id": 13,
      "Active": true,
      "VersionId": 704,
      "Latitude": "50.06542000",
      "Longitude": "28.12813000",
      "FullName": "АЗС №9 05:00 - 21:30",
      "ShortName": "",
      "Address": "Житомирська обл., Чуднівський р-н, с. Дубище, вул. Миру, 6В  ",
      "Region": "Житомирська",
      "LastPriceUpdateDate": "2022-06-04",
      "ServicesAsArray": [
        {
          "id": 1,
          "Title": "Магазин"
        },
        {
          "id": 2,
          "Title": "WC"
        }
      ],
      "FuelsAsArray": [
        {
          "id": 1,
          "Title": "upg DP",
          "Price": "0.00"
        },
        {
          "id": 2,
          "Title": "95 (передоплата)",
          "Price": "0.00"
        },
        {
          "id": 4,
          "Title": "Газ",
          "Price": "0.00"
        },
        {
          "id": 9,
          "Title": "upg 95",
          "Price": "0.00"
        }
      ]
    },
    {
      "id": 17,
      "Active": true,
      "VersionId": 710,
      "Latitude": "50.38957000",
      "Longitude": "29.49398000",
      "FullName": "АЗС №17 05:00 - 21:30",
      "ShortName": "",
      "Address": "Житомирська обл., Брусилівський р-н, с. Йосипівка, вул. Житомирська, 197",
      "Region": "Житомирська",
      "LastPriceUpdateDate": "2022-06-04",
      "ServicesAsArray": [
        {
          "id": 1,
          "Title": "Магазин"
        },
        {
          "id": 2,
          "Title": "WC"
        },
        {
          "id": 3,
          "Title": "Wi-Fi"
        }
      ],
      "FuelsAsArray": [
        {
          "id": 1,
          "Title": "upg DP",
          "Price": "0.00"
        },
        {
          "id": 2,
          "Title": "95 (передоплата)",
          "Price": "0.00"
        },
        {
          "id": 4,
          "Title": "Газ",
          "Price": "37.00"
        },
        {
          "id": 9,
          "Title": "upg 95",
          "Price": "0.00"
        }
      ]
    },
    {
      "id": 67,
      "Active": true,
      "VersionId": 770,
      "Latitude": "51.22757000",
      "Longitude": "27.64627000",
      "FullName": "АЗС №53 05:00 - 23:00",
      "ShortName": "",
      "Address": "Житомирська обл., м. Олевськ, вул. Київська, 7А",
      "Region": "Житомирська",
      "LastPriceUpdateDate": "2022-06-04",
      "ServicesAsArray": [
        {
          "id": 1,
          "Title": "Магазин"
        },
        {
          "id": 2,
          "Title": "WC"
        }
      ],
      "FuelsAsArray": [
        {
          "id": 3,
          "Title": "92 (передоплата)",
          "Price": "0.00"
        },
        {
          "id": 5,
          "Title": "ДП (передоплата)",
          "Price": "0.00"
        },
        {
          "id": 9,
          "Title": "upg 95",
          "Price": "0.00"
        }
      ]
    },
    {
      "id": 75,
      "Active": true,
      "VersionId": 754,
      "Latitude": "50.94013000",
      "Longitude": "28.61512000",
      "FullName": "АЗС №73 05:00 - 23:00",
      "ShortName": "",
      "Address": "Житомирська обл., м. Коростень, вул. Гастелло, 3",
      "Region": "Житомирська",
      "LastPriceUpdateDate": "2022-06-04",
      "ServicesAsArray": [
        {
          "id": 1,
          "Title": "Магазин"
        },
        {
          "id": 2,
          "Title": "WC"
        },
        {
          "id": 5,
          "Title": "Кава"
        }
      ],
      "FuelsAsArray": [
        {
          "id": 1,
          "Title": "upg DP",
          "Price": "0.00"
        },
        {
          "id": 2,
          "Title": "95 (передоплата)",
          "Price": "0.00"
        },
        {
          "id": 4,
          "Title": "Газ",
          "Price": "37.00"
        },
        {
          "id": 9,
          "Title": "upg 95",
          "Price": "49.00"
        }
      ]
    },
    {
      "id": 76,
      "Active": true,
      "VersionId": 919,
      "Latitude": "50.96933000",
      "Longitude": "28.65905000",
      "FullName": "АЗС №74 05:00 - 23:00",
      "ShortName": "",
      "Address": "Житомирська обл., м. Коростень, вул. Жовтнева, 11А",
      "Region": "Житомирська",
      "LastPriceUpdateDate": "2022-06-04",
      "ServicesAsArray": [
        {
          "id": 1,
          "Title": "Магазин"
        },
        {
          "id": 2,
          "Title": "WC"
        },
        {
          "id": 3,
          "Title": "Wi-Fi"
        },
        {
          "id": 4,
          "Title": "Їжа"
        },
        {
          "id": 5,
          "Title": "Кава"
        },
        {
          "id": 6,
          "Title": "Термінал EasyPay"
        },
        {
          "id": 7,
          "Title": "СТО"
        }
      ],
      "FuelsAsArray": [
        {
          "id": 1,
          "Title": "upg DP",
          "Price": "0.00"
        },
        {
          "id": 2,
          "Title": "95 (передоплата)",
          "Price": "0.00"
        },
        {
          "id": 4,
          "Title": "Газ",
          "Price": "0.00"
        },
        {
          "id": 9,
          "Title": "upg 95",
          "Price": "0.00"
        }
      ]
    },
    {
      "id": 104,
      "Active": true,
      "VersionId": 796,
      "Latitude": "51.00350600",
      "Longitude": "28.61395000",
      "FullName": "АЗС №91 05:00 - 23:00",
      "ShortName": "",
      "Address": "Житомирська обл., Коростенський р-н, Кожухівська с/р, а/д М-07 Київ-Ковель-Ягодин, км154-540 ліворуч",
      "Region": "Житомирська",
      "LastPriceUpdateDate": "2022-06-04",
      "ServicesAsArray": [
        {
          "id": 1,
          "Title": "Магазин"
        },
        {
          "id": 2,
          "Title": "WC"
        },
        {
          "id": 3,
          "Title": "Wi-Fi"
        },
        {
          "id": 4,
          "Title": "Їжа"
        },
        {
          "id": 5,
          "Title": "Кава"
        },
        {
          "id": 6,
          "Title": "Термінал EasyPay"
        },
        {
          "id": 8,
          "Title": "Підкачка шин"
        },
        {
          "id": 10,
          "Title": "VIVO-cafe"
        }
      ],
      "FuelsAsArray": [
        {
          "id": 1,
          "Title": "upg DP",
          "Price": "0.00"
        },
        {
          "id": 2,
          "Title": "95 (передоплата)",
          "Price": "0.00"
        },
        {
          "id": 4,
          "Title": "Газ",
          "Price": "37.00"
        },
        {
          "id": 5,
          "Title": "ДП (передоплата)",
          "Price": "0.00"
        },
        {
          "id": 9,
          "Title": "upg 95",
          "Price": "49.00"
        }
      ]
    },
    {
      "id": 111,
      "Active": true,
      "VersionId": 808,
      "Latitude": "50.18057800",
      "Longitude": "28.65524500",
      "FullName": "АЗС №92 05:00 - 21:30",
      "ShortName": "",
      "Address": "Житомирська обл., с. Сінгури, вул. Житомирська (вздовж а/д М-21 Житомир-Могилів-Подільський, км. 10)",
      "Region": "Житомирська",
      "LastPriceUpdateDate": "2022-06-04",
      "ServicesAsArray": [
        {
          "id": 1,
          "Title": "Магазин"
        },
        {
          "id": 2,
          "Title": "WC"
        },
        {
          "id": 3,
          "Title": "Wi-Fi"
        },
        {
          "id": 4,
          "Title": "Їжа"
        },
        {
          "id": 5,
          "Title": "Кава"
        },
        {
          "id": 6,
          "Title": "Термінал EasyPay"
        },
        {
          "id": 8,
          "Title": "Підкачка шин"
        },
        {
          "id": 10,
          "Title": "VIVO-cafe"
        }
      ],
      "FuelsAsArray": [
        {
          "id": 1,
          "Title": "upg DP",
          "Price": "56.00"
        },
        {
          "id": 2,
          "Title": "95 (передоплата)",
          "Price": "0.00"
        },
        {
          "id": 4,
          "Title": "Газ",
          "Price": "0.00"
        },
        {
          "id": 5,
          "Title": "ДП (передоплата)",
          "Price": "0.00"
        },
        {
          "id": 9,
          "Title": "upg 95",
          "Price": "0.00"
        }
      ]
    },
    {
      "id": 144,
      "Active": true,
      "VersionId": 884,
      "Latitude": "50.27340400",
      "Longitude": "28.66440000",
      "FullName": "АЗС №115 05:00 - 21:30",
      "ShortName": "",
      "Address": "Житомирська обл., м. Житомир, проспект Незалежності, 29",
      "Region": "Житомирська",
      "LastPriceUpdateDate": "2022-06-04",
      "ServicesAsArray": [
        {
          "id": 1,
          "Title": "Магазин"
        },
        {
          "id": 2,
          "Title": "WC"
        },
        {
          "id": 3,
          "Title": "Wi-Fi"
        },
        {
          "id": 4,
          "Title": "Їжа"
        },
        {
          "id": 5,
          "Title": "Кава"
        },
        {
          "id": 6,
          "Title": "Термінал EasyPay"
        },
        {
          "id": 8,
          "Title": "Підкачка шин"
        },
        {
          "id": 10,
          "Title": "VIVO-cafe"
        }
      ],
      "FuelsAsArray": [
        {
          "id": 1,
          "Title": "upg DP",
          "Price": "0.00"
        },
        {
          "id": 2,
          "Title": "95 (передоплата)",
          "Price": "0.00"
        },
        {
          "id": 4,
          "Title": "Газ",
          "Price": "0.00"
        },
        {
          "id": 5,
          "Title": "ДП (передоплата)",
          "Price": "0.00"
        },
        {
          "id": 9,
          "Title": "upg 95",
          "Price": "49.00"
        }
      ]
    },
    {
      "id": 56,
      "Active": true,
      "VersionId": 722,
      "Latitude": "48.57790000",
      "Longitude": "22.29922000",
      "FullName": "АЗС №54 00:00 - 24:00",
      "ShortName": "",
      "Address": "Закарпатська обл., Ужгородський р-н, с. Кінчеш, автошлях Кінчеш-Розівка, 9 км",
      "Region": "Закарпатська",
      "LastPriceUpdateDate": "2022-06-04",
      "ServicesAsArray": [
        {
          "id": 1,
          "Title": "Магазин"
        },
        {
          "id": 2,
          "Title": "WC"
        },
        {
          "id": 6,
          "Title": "Термінал EasyPay"
        }
      ],
      "FuelsAsArray": [
        {
          "id": 3,
          "Title": "92 (передоплата)",
          "Price": "0.00"
        },
        {
          "id": 5,
          "Title": "ДП (передоплата)",
          "Price": "0.00"
        },
        {
          "id": 9,
          "Title": "upg 95",
          "Price": "0.00"
        }
      ]
    },
    {
      "id": 57,
      "Active": true,
      "VersionId": 726,
      "Latitude": "48.02237000",
      "Longitude": "23.54452000",
      "FullName": "АЗС №55 00:00 - 24:00",
      "ShortName": "",
      "Address": "Закарпатська обл, м. Тячів, вул. Армійська, 125А",
      "Region": "Закарпатська",
      "LastPriceUpdateDate": "2022-06-04",
      "ServicesAsArray": [
        {
          "id": 1,
          "Title": "Магазин"
        },
        {
          "id": 2,
          "Title": "WC"
        },
        {
          "id": 6,
          "Title": "Термінал EasyPay"
        }
      ],
      "FuelsAsArray": [
        {
          "id": 2,
          "Title": "95 (передоплата)",
          "Price": "0.00"
        },
        {
          "id": 4,
          "Title": "Газ",
          "Price": "37.00"
        },
        {
          "id": 5,
          "Title": "ДП (передоплата)",
          "Price": "0.00"
        },
        {
          "id": 9,
          "Title": "upg 95",
          "Price": "0.00"
        }
      ]
    },
    {
      "id": 97,
      "Active": true,
      "VersionId": 784,
      "Latitude": "48.20485000",
      "Longitude": "23.31642000",
      "FullName": "АЗС №87 00:00 - 24:00",
      "ShortName": "",
      "Address": "Закарпатська обл., Хустський р-н, с. Іза, вул. Центральна, б/н",
      "Region": "Закарпатська",
      "LastPriceUpdateDate": "2022-06-04",
      "ServicesAsArray": [
        {
          "id": 1,
          "Title": "Магазин"
        }
      ],
      "FuelsAsArray": [
        {
          "id": 2,
          "Title": "95 (передоплата)",
          "Price": "0.00"
        },
        {
          "id": 5,
          "Title": "ДП (передоплата)",
          "Price": "0.00"
        },
        {
          "id": 9,
          "Title": "upg 95",
          "Price": "0.00"
        }
      ]
    },
    {
      "id": 120,
      "Active": true,
      "VersionId": 826,
      "Latitude": "48.55135300",
      "Longitude": "22.99051900",
      "FullName": "АЗС №98 00:00 - 24:00",
      "ShortName": "",
      "Address": "Закарпатська обл., м. Свалява, вул. Борканюка, 42 ",
      "Region": "Закарпатська",
      "LastPriceUpdateDate": "2022-06-04",
      "ServicesAsArray": [
        {
          "id": 1,
          "Title": "Магазин"
        }
      ],
      "FuelsAsArray": [
        {
          "id": 2,
          "Title": "95 (передоплата)",
          "Price": "0.00"
        },
        {
          "id": 5,
          "Title": "ДП (передоплата)",
          "Price": "0.00"
        },
        {
          "id": 9,
          "Title": "upg 95",
          "Price": "49.00"
        }
      ]
    },
    {
      "id": 130,
      "Active": true,
      "VersionId": 846,
      "Latitude": "48.45829000",
      "Longitude": "22.70718000",
      "FullName": "АЗС №102 00:00 - 24:00",
      "ShortName": "",
      "Address": "Закарпатська обл., м. Мукачево, вул. Лавківська, 1Ж",
      "Region": "Закарпатська",
      "LastPriceUpdateDate": "2022-06-04",
      "ServicesAsArray": [
        {
          "id": 1,
          "Title": "Магазин"
        },
        {
          "id": 2,
          "Title": "WC"
        },
        {
          "id": 3,
          "Title": "Wi-Fi"
        },
        {
          "id": 4,
          "Title": "Їжа"
        },
        {
          "id": 5,
          "Title": "Кава"
        },
        {
          "id": 6,
          "Title": "Термінал EasyPay"
        },
        {
          "id": 10,
          "Title": "VIVO-cafe"
        }
      ],
      "FuelsAsArray": [
        {
          "id": 2,
          "Title": "95 (передоплата)",
          "Price": "0.00"
        },
        {
          "id": 4,
          "Title": "Газ",
          "Price": "37.00"
        },
        {
          "id": 5,
          "Title": "ДП (передоплата)",
          "Price": "0.00"
        },
        {
          "id": 9,
          "Title": "upg 95",
          "Price": "0.00"
        }
      ]
    },
    {
      "id": 82,
      "Active": false,
      "VersionId": 670,
      "Latitude": "48.27287000",
      "Longitude": "22.46157000",
      "FullName": "АЗС №76",
      "ShortName": "",
      "Address": "Закарпатська обл., Берегівський р-н, с. Косонь, вул. Кошут Лайош, 151Б",
      "Region": "Закарпатська",
      "LastPriceUpdateDate": "2022-06-04",
      "ServicesAsArray": [
        {
          "id": 1,
          "Title": "Магазин"
        },
        {
          "id": 2,
          "Title": "WC"
        }
      ],
      "FuelsAsArray": [
        {
          "id": 2,
          "Title": "95 (передоплата)",
          "Price": "0.00"
        },
        {
          "id": 3,
          "Title": "92 (передоплата)",
          "Price": "0.00"
        },
        {
          "id": 4,
          "Title": "Газ",
          "Price": "0.00"
        },
        {
          "id": 5,
          "Title": "ДП (передоплата)",
          "Price": "0.00"
        }
      ]
    },
    {
      "id": 46,
      "Active": true,
      "VersionId": 688,
      "Latitude": "47.85370000",
      "Longitude": "35.23080000",
      "FullName": "АЗС №43 05:00 - 21:00",
      "ShortName": "",
      "Address": "Запорізька обл., м. Запоріжжя, вул. Авраменка, 23",
      "Region": "Запорізька",
      "LastPriceUpdateDate": "2022-06-04",
      "ServicesAsArray": [
        {
          "id": 1,
          "Title": "Магазин"
        },
        {
          "id": 2,
          "Title": "WC"
        }
      ],
      "FuelsAsArray": [
        {
          "id": 1,
          "Title": "upg DP",
          "Price": "0.00"
        },
        {
          "id": 2,
          "Title": "95 (передоплата)",
          "Price": "0.00"
        },
        {
          "id": 4,
          "Title": "Газ",
          "Price": "37.00"
        },
        {
          "id": 9,
          "Title": "upg 95",
          "Price": "0.00"
        }
      ]
    },
    {
      "id": 47,
      "Active": true,
      "VersionId": 690,
      "Latitude": "47.85047000",
      "Longitude": "35.14637000",
      "FullName": "АЗС №44 05:00 - 21:00",
      "ShortName": "",
      "Address": "Запорізька обл., м. Запоріжжя, вул. Адмірала Нахімова, 3",
      "Region": "Запорізька",
      "LastPriceUpdateDate": "2022-06-04",
      "ServicesAsArray": [
        {
          "id": 1,
          "Title": "Магазин"
        }
      ],
      "FuelsAsArray": [
        {
          "id": 1,
          "Title": "upg DP",
          "Price": "0.00"
        },
        {
          "id": 2,
          "Title": "95 (передоплата)",
          "Price": "0.00"
        },
        {
          "id": 9,
          "Title": "upg 95",
          "Price": "0.00"
        }
      ]
    },
    {
      "id": 45,
      "Active": false,
      "VersionId": 686,
      "Latitude": "47.49067000",
      "Longitude": "36.17702000",
      "FullName": "АЗС №42",
      "ShortName": "",
      "Address": "Запорізька обл., м. Пологи, вул. К. Маркса, 530В",
      "Region": "Запорізька",
      "LastPriceUpdateDate": "2022-06-04",
      "ServicesAsArray": [
        {
          "id": 1,
          "Title": "Магазин"
        },
        {
          "id": 2,
          "Title": "WC"
        }
      ],
      "FuelsAsArray": [
        {
          "id": 2,
          "Title": "95 (передоплата)",
          "Price": "0.00"
        },
        {
          "id": 3,
          "Title": "92 (передоплата)",
          "Price": "0.00"
        },
        {
          "id": 4,
          "Title": "Газ",
          "Price": "0.00"
        },
        {
          "id": 5,
          "Title": "ДП (передоплата)",
          "Price": "0.00"
        }
      ]
    },
    {
      "id": 48,
      "Active": false,
      "VersionId": 718,
      "Latitude": "46.73527000",
      "Longitude": "36.32850000",
      "FullName": "АЗС №45",
      "ShortName": "",
      "Address": "Запорізька обл., м. Приморськ, Мелітопольське шосе, 7",
      "Region": "Запорізька",
      "LastPriceUpdateDate": "2022-06-04",
      "ServicesAsArray": [
        {
          "id": 1,
          "Title": "Магазин"
        },
        {
          "id": 2,
          "Title": "WC"
        }
      ],
      "FuelsAsArray": [
        {
          "id": 2,
          "Title": "95 (передоплата)",
          "Price": "0.00"
        },
        {
          "id": 3,
          "Title": "92 (передоплата)",
          "Price": "0.00"
        },
        {
          "id": 4,
          "Title": "Газ",
          "Price": "0.00"
        },
        {
          "id": 5,
          "Title": "ДП (передоплата)",
          "Price": "0.00"
        }
      ]
    },
    {
      "id": 49,
      "Active": false,
      "VersionId": 720,
      "Latitude": "47.38522000",
      "Longitude": "35.01497000",
      "FullName": "АЗС №46",
      "ShortName": "",
      "Address": "Запорізька обл., м. Дніпрорудне, вул. Нижня, 62",
      "Region": "Запорізька",
      "LastPriceUpdateDate": "2022-06-04",
      "ServicesAsArray": [
        {
          "id": 1,
          "Title": "Магазин"
        },
        {
          "id": 2,
          "Title": "WC"
        }
      ],
      "FuelsAsArray": [
        {
          "id": 2,
          "Title": "95 (передоплата)",
          "Price": "0.00"
        },
        {
          "id": 3,
          "Title": "92 (передоплата)",
          "Price": "0.00"
        },
        {
          "id": 4,
          "Title": "Газ",
          "Price": "0.00"
        },
        {
          "id": 5,
          "Title": "ДП (передоплата)",
          "Price": "0.00"
        },
        {
          "id": 8,
          "Title": "upg 100",
          "Price": "0.00"
        }
      ]
    },
    {
      "id": 155,
      "Active": true,
      "VersionId": 990,
      "Latitude": "48.48965600",
      "Longitude": "24.59504200",
      "FullName": "АЗС №129 05:00 - 23:00",
      "ShortName": "",
      "Address": "Івано-Франківська обл., м. Яремче, вул. Свободи",
      "Region": "Івано-Франківська",
      "LastPriceUpdateDate": "2022-06-04",
      "ServicesAsArray": [
        {
          "id": 1,
          "Title": "Магазин"
        },
        {
          "id": 2,
          "Title": "WC"
        },
        {
          "id": 3,
          "Title": "Wi-Fi"
        },
        {
          "id": 4,
          "Title": "Їжа"
        },
        {
          "id": 5,
          "Title": "Кава"
        },
        {
          "id": 6,
          "Title": "Термінал EasyPay"
        },
        {
          "id": 7,
          "Title": "СТО"
        },
        {
          "id": 8,
          "Title": "Підкачка шин"
        },
        {
          "id": 10,
          "Title": "VIVO-cafe"
        }
      ],
      "FuelsAsArray": [
        {
          "id": 1,
          "Title": "upg DP",
          "Price": "0.00"
        },
        {
          "id": 2,
          "Title": "95 (передоплата)",
          "Price": "0.00"
        },
        {
          "id": 4,
          "Title": "Газ",
          "Price": "37.00"
        },
        {
          "id": 9,
          "Title": "upg 95",
          "Price": "0.00"
        }
      ]
    },
    {
      "id": 156,
      "Active": true,
      "VersionId": 978,
      "Latitude": "48.84618600",
      "Longitude": "24.70587600",
      "FullName": "АЗС №130 05:00 - 23:00",
      "ShortName": "",
      "Address": "Івано-Франківська обл., Тисменецький р-н, с. Черніїв, ур. Біля водоканалу",
      "Region": "Івано-Франківська",
      "LastPriceUpdateDate": "2022-06-04",
      "ServicesAsArray": [
        {
          "id": 1,
          "Title": "Магазин"
        },
        {
          "id": 2,
          "Title": "WC"
        },
        {
          "id": 3,
          "Title": "Wi-Fi"
        },
        {
          "id": 4,
          "Title": "Їжа"
        },
        {
          "id": 5,
          "Title": "Кава"
        },
        {
          "id": 6,
          "Title": "Термінал EasyPay"
        },
        {
          "id": 8,
          "Title": "Підкачка шин"
        },
        {
          "id": 10,
          "Title": "VIVO-cafe"
        }
      ],
      "FuelsAsArray": [
        {
          "id": 1,
          "Title": "upg DP",
          "Price": "0.00"
        },
        {
          "id": 2,
          "Title": "95 (передоплата)",
          "Price": "0.00"
        },
        {
          "id": 4,
          "Title": "Газ",
          "Price": "37.00"
        },
        {
          "id": 5,
          "Title": "ДП (передоплата)",
          "Price": "0.00"
        },
        {
          "id": 9,
          "Title": "upg 95",
          "Price": "0.00"
        }
      ]
    },
    {
      "id": 19,
      "Active": true,
      "VersionId": 714,
      "Latitude": "50.22152000",
      "Longitude": "31.63245000",
      "FullName": "АЗС №19 06:00 - 21:00",
      "ShortName": "",
      "Address": "Київська обл., Переяслав-Хмельницький р-н, с/рада Студениківська, автошлях Київ-Харків, 91 км",
      "Region": "Київська",
      "LastPriceUpdateDate": "2022-06-04",
      "ServicesAsArray": [
        {
          "id": 1,
          "Title": "Магазин"
        },
        {
          "id": 2,
          "Title": "WC"
        }
      ],
      "FuelsAsArray": [
        {
          "id": 2,
          "Title": "95 (передоплата)",
          "Price": "0.00"
        },
        {
          "id": 4,
          "Title": "Газ",
          "Price": "0.00"
        },
        {
          "id": 5,
          "Title": "ДП (передоплата)",
          "Price": "0.00"
        },
        {
          "id": 9,
          "Title": "upg 95",
          "Price": "0.00"
        }
      ]
    },
    {
      "id": 20,
      "Active": true,
      "VersionId": 716,
      "Latitude": "50.08748000",
      "Longitude": "30.23500000",
      "FullName": "АЗС №20 07:00 - 19:00",
      "ShortName": "",
      "Address": "Київська обл., Васильківський р-н, с/рада Кодаківська, автошлях Київ-Одеса, 50 км + 700 м",
      "Region": "Київська",
      "LastPriceUpdateDate": "2022-06-04",
      "ServicesAsArray": [
        {
          "id": 1,
          "Title": "Магазин"
        },
        {
          "id": 2,
          "Title": "WC"
        }
      ],
      "FuelsAsArray": [
        {
          "id": 1,
          "Title": "upg DP",
          "Price": "0.00"
        },
        {
          "id": 2,
          "Title": "95 (передоплата)",
          "Price": "0.00"
        },
        {
          "id": 4,
          "Title": "Газ",
          "Price": "0.00"
        },
        {
          "id": 5,
          "Title": "ДП (передоплата)",
          "Price": "0.00"
        },
        {
          "id": 9,
          "Title": "upg 95",
          "Price": "0.00"
        }
      ]
    },
    {
      "id": 93,
      "Active": true,
      "VersionId": 778,
      "Latitude": "50.27222000",
      "Longitude": "30.53598000",
      "FullName": "АЗС №79 05:00 - 23:00",
      "ShortName": "",
      "Address": "Київська обл., Києво-Святошинський р-н, с. Ходосівка, вул. Обухівське шосе, 1",
      "Region": "Київська",
      "LastPriceUpdateDate": "2022-06-04",
      "ServicesAsArray": [
        {
          "id": 1,
          "Title": "Магазин"
        },
        {
          "id": 2,
          "Title": "WC"
        },
        {
          "id": 5,
          "Title": "Кава"
        },
        {
          "id": 6,
          "Title": "Термінал EasyPay"
        }
      ],
      "FuelsAsArray": [
        {
          "id": 2,
          "Title": "95 (передоплата)",
          "Price": "0.00"
        },
        {
          "id": 4,
          "Title": "Газ",
          "Price": "0.00"
        },
        {
          "id": 5,
          "Title": "ДП (передоплата)",
          "Price": "0.00"
        },
        {
          "id": 9,
          "Title": "upg 95",
          "Price": "0.00"
        }
      ]
    },
    {
      "id": 101,
      "Active": true,
      "VersionId": 790,
      "Latitude": "50.55509100",
      "Longitude": "30.24865200",
      "FullName": "АЗС №89 05:00 - 23:00",
      "ShortName": "",
      "Address": "Київська обл., м. Буча, вул. Шевченка, 4А",
      "Region": "Київська",
      "LastPriceUpdateDate": "2022-06-04",
      "ServicesAsArray": [
        {
          "id": 1,
          "Title": "Магазин"
        },
        {
          "id": 2,
          "Title": "WC"
        },
        {
          "id": 3,
          "Title": "Wi-Fi"
        },
        {
          "id": 4,
          "Title": "Їжа"
        },
        {
          "id": 5,
          "Title": "Кава"
        },
        {
          "id": 6,
          "Title": "Термінал EasyPay"
        },
        {
          "id": 8,
          "Title": "Підкачка шин"
        },
        {
          "id": 10,
          "Title": "VIVO-cafe"
        }
      ],
      "FuelsAsArray": [
        {
          "id": 1,
          "Title": "upg DP",
          "Price": "0.00"
        },
        {
          "id": 2,
          "Title": "95 (передоплата)",
          "Price": "0.00"
        },
        {
          "id": 5,
          "Title": "ДП (передоплата)",
          "Price": "0.00"
        },
        {
          "id": 9,
          "Title": "upg 95",
          "Price": "0.00"
        }
      ]
    },
    {
      "id": 106,
      "Active": true,
      "VersionId": 800,
      "Latitude": "50.40053000",
      "Longitude": "30.40917000",
      "FullName": "АЗС №90 05:00 - 21:50",
      "ShortName": "",
      "Address": "Київська обл., Києво-Святошинський р-н, а/д Т 10-27 Київське півкільце, 12+363-12+552 км (праворуч)",
      "Region": "Київська",
      "LastPriceUpdateDate": "2022-06-04",
      "ServicesAsArray": [
        {
          "id": 1,
          "Title": "Магазин"
        },
        {
          "id": 2,
          "Title": "WC"
        },
        {
          "id": 3,
          "Title": "Wi-Fi"
        },
        {
          "id": 4,
          "Title": "Їжа"
        },
        {
          "id": 5,
          "Title": "Кава"
        },
        {
          "id": 6,
          "Title": "Термінал EasyPay"
        },
        {
          "id": 8,
          "Title": "Підкачка шин"
        },
        {
          "id": 10,
          "Title": "VIVO-cafe"
        }
      ],
      "FuelsAsArray": [
        {
          "id": 1,
          "Title": "upg DP",
          "Price": "0.00"
        },
        {
          "id": 2,
          "Title": "95 (передоплата)",
          "Price": "0.00"
        },
        {
          "id": 4,
          "Title": "Газ",
          "Price": "0.00"
        },
        {
          "id": 5,
          "Title": "ДП (передоплата)",
          "Price": "0.00"
        },
        {
          "id": 9,
          "Title": "upg 95",
          "Price": "49.00"
        }
      ]
    },
    {
      "id": 118,
      "Active": true,
      "VersionId": 822,
      "Latitude": "50.38567000",
      "Longitude": "30.79032000",
      "FullName": "АЗС №96 05:00 - 23:00",
      "ShortName": "",
      "Address": "Київська обл, Бориспільський р-н, с. Щасливе, Харківське шосе, 13",
      "Region": "Київська",
      "LastPriceUpdateDate": "2022-06-04",
      "ServicesAsArray": [
        {
          "id": 1,
          "Title": "Магазин"
        },
        {
          "id": 2,
          "Title": "WC"
        },
        {
          "id": 3,
          "Title": "Wi-Fi"
        },
        {
          "id": 4,
          "Title": "Їжа"
        },
        {
          "id": 5,
          "Title": "Кава"
        },
        {
          "id": 6,
          "Title": "Термінал EasyPay"
        },
        {
          "id": 8,
          "Title": "Підкачка шин"
        },
        {
          "id": 10,
          "Title": "VIVO-cafe"
        }
      ],
      "FuelsAsArray": [
        {
          "id": 1,
          "Title": "upg DP",
          "Price": "0.00"
        },
        {
          "id": 2,
          "Title": "95 (передоплата)",
          "Price": "0.00"
        },
        {
          "id": 4,
          "Title": "Газ",
          "Price": "0.00"
        },
        {
          "id": 5,
          "Title": "ДП (передоплата)",
          "Price": "0.00"
        },
        {
          "id": 9,
          "Title": "upg 95",
          "Price": "0.00"
        }
      ]
    },
    {
      "id": 123,
      "Active": true,
      "VersionId": 828,
      "Latitude": "50.38154600",
      "Longitude": "30.83435400",
      "FullName": "АЗС №99 05:00 - 23:00",
      "ShortName": "",
      "Address": "Київська обл., Бориспільський р-н, с. Чубинське, вул. Київська, 1В",
      "Region": "Київська",
      "LastPriceUpdateDate": "2022-06-04",
      "ServicesAsArray": [
        {
          "id": 1,
          "Title": "Магазин"
        },
        {
          "id": 2,
          "Title": "WC"
        },
        {
          "id": 3,
          "Title": "Wi-Fi"
        },
        {
          "id": 4,
          "Title": "Їжа"
        },
        {
          "id": 5,
          "Title": "Кава"
        },
        {
          "id": 6,
          "Title": "Термінал EasyPay"
        },
        {
          "id": 8,
          "Title": "Підкачка шин"
        },
        {
          "id": 10,
          "Title": "VIVO-cafe"
        }
      ],
      "FuelsAsArray": [
        {
          "id": 2,
          "Title": "95 (передоплата)",
          "Price": "0.00"
        },
        {
          "id": 4,
          "Title": "Газ",
          "Price": "37.00"
        },
        {
          "id": 5,
          "Title": "ДП (передоплата)",
          "Price": "0.00"
        },
        {
          "id": 9,
          "Title": "upg 95",
          "Price": "0.00"
        }
      ]
    },
    {
      "id": 128,
      "Active": true,
      "VersionId": 842,
      "Latitude": "50.35567000",
      "Longitude": "30.43601000",
      "FullName": "АЗС №101 05:00 - 23:00",
      "ShortName": "",
      "Address": "Київська обл., Києво-Святошинський р-н, с. Гатне, вул. Інститутська, 14",
      "Region": "Київська",
      "LastPriceUpdateDate": "2022-06-04",
      "ServicesAsArray": [
        {
          "id": 1,
          "Title": "Магазин"
        },
        {
          "id": 2,
          "Title": "WC"
        },
        {
          "id": 3,
          "Title": "Wi-Fi"
        },
        {
          "id": 4,
          "Title": "Їжа"
        },
        {
          "id": 5,
          "Title": "Кава"
        },
        {
          "id": 6,
          "Title": "Термінал EasyPay"
        },
        {
          "id": 8,
          "Title": "Підкачка шин"
        },
        {
          "id": 10,
          "Title": "VIVO-cafe"
        }
      ],
      "FuelsAsArray": [
        {
          "id": 1,
          "Title": "upg DP",
          "Price": "0.00"
        },
        {
          "id": 2,
          "Title": "95 (передоплата)",
          "Price": "0.00"
        },
        {
          "id": 4,
          "Title": "Газ",
          "Price": "0.00"
        },
        {
          "id": 5,
          "Title": "ДП (передоплата)",
          "Price": "0.00"
        },
        {
          "id": 9,
          "Title": "upg 95",
          "Price": "0.00"
        }
      ]
    },
    {
      "id": 134,
      "Active": true,
      "VersionId": 854,
      "Latitude": "50.42384700",
      "Longitude": "30.63747100",
      "FullName": "АЗС №109 05:00 - 23:00",
      "ShortName": "",
      "Address": "м. Київ, Дарницький р-н, вул. Затишна, 3",
      "Region": "Київська",
      "LastPriceUpdateDate": "2022-06-04",
      "ServicesAsArray": [
        {
          "id": 1,
          "Title": "Магазин"
        },
        {
          "id": 2,
          "Title": "WC"
        },
        {
          "id": 3,
          "Title": "Wi-Fi"
        },
        {
          "id": 4,
          "Title": "Їжа"
        },
        {
          "id": 5,
          "Title": "Кава"
        },
        {
          "id": 6,
          "Title": "Термінал EasyPay"
        },
        {
          "id": 8,
          "Title": "Підкачка шин"
        },
        {
          "id": 10,
          "Title": "VIVO-cafe"
        }
      ],
      "FuelsAsArray": [
        {
          "id": 1,
          "Title": "upg DP",
          "Price": "0.00"
        },
        {
          "id": 2,
          "Title": "95 (передоплата)",
          "Price": "0.00"
        },
        {
          "id": 4,
          "Title": "Газ",
          "Price": "0.00"
        },
        {
          "id": 5,
          "Title": "ДП (передоплата)",
          "Price": "0.00"
        },
        {
          "id": 9,
          "Title": "upg 95",
          "Price": "0.00"
        }
      ]
    },
    {
      "id": 142,
      "Active": true,
      "VersionId": 864,
      "Latitude": "50.33997900",
      "Longitude": "30.41372200",
      "FullName": "АЗС №118 05:00 - 23:00",
      "ShortName": "",
      "Address": "Київська обл., Києво-Святошинський р-н, смт Чабани, вул. Одеське шосе, 15",
      "Region": "Київська",
      "LastPriceUpdateDate": "2022-06-04",
      "ServicesAsArray": [
        {
          "id": 1,
          "Title": "Магазин"
        },
        {
          "id": 2,
          "Title": "WC"
        },
        {
          "id": 3,
          "Title": "Wi-Fi"
        },
        {
          "id": 4,
          "Title": "Їжа"
        },
        {
          "id": 5,
          "Title": "Кава"
        },
        {
          "id": 6,
          "Title": "Термінал EasyPay"
        },
        {
          "id": 8,
          "Title": "Підкачка шин"
        },
        {
          "id": 10,
          "Title": "VIVO-cafe"
        }
      ],
      "FuelsAsArray": [
        {
          "id": 1,
          "Title": "upg DP",
          "Price": "0.00"
        },
        {
          "id": 2,
          "Title": "95 (передоплата)",
          "Price": "0.00"
        },
        {
          "id": 4,
          "Title": "Газ",
          "Price": "0.00"
        },
        {
          "id": 5,
          "Title": "ДП (передоплата)",
          "Price": "0.00"
        },
        {
          "id": 9,
          "Title": "upg 95",
          "Price": "0.00"
        }
      ]
    },
    {
      "id": 145,
      "Active": true,
      "VersionId": 880,
      "Latitude": "50.34454900",
      "Longitude": "30.27985900",
      "FullName": "АЗС №119 05:00 - 23:00",
      "ShortName": "",
      "Address": "Київська обл., Києво-Святошинський р-н, м. Боярка, вул. Магістральна, 32",
      "Region": "Київська",
      "LastPriceUpdateDate": "2022-06-04",
      "ServicesAsArray": [
        {
          "id": 1,
          "Title": "Магазин"
        },
        {
          "id": 2,
          "Title": "WC"
        },
        {
          "id": 3,
          "Title": "Wi-Fi"
        },
        {
          "id": 4,
          "Title": "Їжа"
        },
        {
          "id": 5,
          "Title": "Кава"
        },
        {
          "id": 6,
          "Title": "Термінал EasyPay"
        },
        {
          "id": 8,
          "Title": "Підкачка шин"
        },
        {
          "id": 10,
          "Title": "VIVO-cafe"
        }
      ],
      "FuelsAsArray": [
        {
          "id": 1,
          "Title": "upg DP",
          "Price": "0.00"
        },
        {
          "id": 2,
          "Title": "95 (передоплата)",
          "Price": "0.00"
        },
        {
          "id": 4,
          "Title": "Газ",
          "Price": "0.00"
        },
        {
          "id": 5,
          "Title": "ДП (передоплата)",
          "Price": "0.00"
        },
        {
          "id": 9,
          "Title": "upg 95",
          "Price": "49.00"
        }
      ]
    },
    {
      "id": 146,
      "Active": true,
      "VersionId": 916,
      "Latitude": "50.42228480",
      "Longitude": "30.61182990",
      "FullName": "АЗС №120 06:00 - 21:00",
      "ShortName": "",
      "Address": "м. Київ, вул. Канальна, 7",
      "Region": "Київська",
      "LastPriceUpdateDate": "2022-06-04",
      "ServicesAsArray": [
        {
          "id": 1,
          "Title": "Магазин"
        },
        {
          "id": 2,
          "Title": "WC"
        },
        {
          "id": 3,
          "Title": "Wi-Fi"
        },
        {
          "id": 4,
          "Title": "Їжа"
        },
        {
          "id": 5,
          "Title": "Кава"
        },
        {
          "id": 6,
          "Title": "Термінал EasyPay"
        },
        {
          "id": 10,
          "Title": "VIVO-cafe"
        }
      ],
      "FuelsAsArray": [
        {
          "id": 1,
          "Title": "upg DP",
          "Price": "0.00"
        },
        {
          "id": 2,
          "Title": "95 (передоплата)",
          "Price": "0.00"
        },
        {
          "id": 4,
          "Title": "Газ",
          "Price": "0.00"
        },
        {
          "id": 5,
          "Title": "ДП (передоплата)",
          "Price": "0.00"
        },
        {
          "id": 9,
          "Title": "upg 95",
          "Price": "0.00"
        }
      ]
    },
    {
      "id": 149,
      "Active": true,
      "VersionId": 942,
      "Latitude": "50.50617700",
      "Longitude": "30.41187200",
      "FullName": "АЗС №123 05:00 - 22:30",
      "ShortName": "",
      "Address": "м. Київ, проспект Правди, 47",
      "Region": "Київська",
      "LastPriceUpdateDate": "2022-06-04",
      "ServicesAsArray": [
        {
          "id": 1,
          "Title": "Магазин"
        },
        {
          "id": 2,
          "Title": "WC"
        },
        {
          "id": 3,
          "Title": "Wi-Fi"
        },
        {
          "id": 4,
          "Title": "Їжа"
        },
        {
          "id": 5,
          "Title": "Кава"
        },
        {
          "id": 6,
          "Title": "Термінал EasyPay"
        },
        {
          "id": 8,
          "Title": "Підкачка шин"
        },
        {
          "id": 10,
          "Title": "VIVO-cafe"
        }
      ],
      "FuelsAsArray": [
        {
          "id": 1,
          "Title": "upg DP",
          "Price": "0.00"
        },
        {
          "id": 2,
          "Title": "95 (передоплата)",
          "Price": "0.00"
        },
        {
          "id": 4,
          "Title": "Газ",
          "Price": "0.00"
        },
        {
          "id": 5,
          "Title": "ДП (передоплата)",
          "Price": "0.00"
        },
        {
          "id": 9,
          "Title": "upg 95",
          "Price": "0.00"
        }
      ]
    },
    {
      "id": 150,
      "Active": true,
      "VersionId": 936,
      "Latitude": "50.31919200",
      "Longitude": "31.02826900",
      "FullName": "АЗС №124 06:00 - 21:00",
      "ShortName": "",
      "Address": "Київська обл., Бориспільський р-н, с. Іванків, вул. Харківська, 1С",
      "Region": "Київська",
      "LastPriceUpdateDate": "2022-06-04",
      "ServicesAsArray": [
        {
          "id": 1,
          "Title": "Магазин"
        },
        {
          "id": 2,
          "Title": "WC"
        },
        {
          "id": 3,
          "Title": "Wi-Fi"
        },
        {
          "id": 4,
          "Title": "Їжа"
        },
        {
          "id": 5,
          "Title": "Кава"
        },
        {
          "id": 6,
          "Title": "Термінал EasyPay"
        },
        {
          "id": 8,
          "Title": "Підкачка шин"
        },
        {
          "id": 10,
          "Title": "VIVO-cafe"
        }
      ],
      "FuelsAsArray": [
        {
          "id": 2,
          "Title": "95 (передоплата)",
          "Price": "0.00"
        },
        {
          "id": 4,
          "Title": "Газ",
          "Price": "0.00"
        },
        {
          "id": 5,
          "Title": "ДП (передоплата)",
          "Price": "0.00"
        },
        {
          "id": 9,
          "Title": "upg 95",
          "Price": "49.00"
        }
      ]
    },
    {
      "id": 157,
      "Active": true,
      "VersionId": 992,
      "Latitude": "50.46105000",
      "Longitude": "30.60075900",
      "FullName": "АЗС №131 05:00 - 22:30",
      "ShortName": "",
      "Address": "м. Київ, проспект Визволителів, 13",
      "Region": "Київська",
      "LastPriceUpdateDate": "2022-06-04",
      "ServicesAsArray": [
        {
          "id": 1,
          "Title": "Магазин"
        },
        {
          "id": 2,
          "Title": "WC"
        },
        {
          "id": 3,
          "Title": "Wi-Fi"
        },
        {
          "id": 4,
          "Title": "Їжа"
        },
        {
          "id": 5,
          "Title": "Кава"
        },
        {
          "id": 6,
          "Title": "Термінал EasyPay"
        },
        {
          "id": 8,
          "Title": "Підкачка шин"
        },
        {
          "id": 10,
          "Title": "VIVO-cafe"
        }
      ],
      "FuelsAsArray": [
        {
          "id": 1,
          "Title": "upg DP",
          "Price": "0.00"
        },
        {
          "id": 2,
          "Title": "95 (передоплата)",
          "Price": "0.00"
        },
        {
          "id": 4,
          "Title": "Газ",
          "Price": "0.00"
        },
        {
          "id": 5,
          "Title": "ДП (передоплата)",
          "Price": "0.00"
        },
        {
          "id": 9,
          "Title": "upg 95",
          "Price": "0.00"
        }
      ]
    },
    {
      "id": 121,
      "Active": false,
      "VersionId": 988,
      "Latitude": "50.44031700",
      "Longitude": "30.14727700",
      "FullName": "АЗС №97",
      "ShortName": "",
      "Address": "Київська обл., Києво-Святошинський р-н,територія Дмитрівської С/Р,траса М06, Київ-Львів-Чоп27км+700м",
      "Region": "Київська",
      "LastPriceUpdateDate": "2022-06-04",
      "ServicesAsArray": [
        {
          "id": 1,
          "Title": "Магазин"
        },
        {
          "id": 2,
          "Title": "WC"
        },
        {
          "id": 3,
          "Title": "Wi-Fi"
        },
        {
          "id": 4,
          "Title": "Їжа"
        },
        {
          "id": 5,
          "Title": "Кава"
        },
        {
          "id": 6,
          "Title": "Термінал EasyPay"
        },
        {
          "id": 8,
          "Title": "Підкачка шин"
        },
        {
          "id": 10,
          "Title": "VIVO-cafe"
        }
      ],
      "FuelsAsArray": [
        {
          "id": 2,
          "Title": "95 (передоплата)",
          "Price": "0.00"
        },
        {
          "id": 3,
          "Title": "92 (передоплата)",
          "Price": "0.00"
        },
        {
          "id": 4,
          "Title": "Газ",
          "Price": "0.00"
        },
        {
          "id": 5,
          "Title": "ДП (передоплата)",
          "Price": "0.00"
        },
        {
          "id": 8,
          "Title": "upg 100",
          "Price": "0.00"
        }
      ]
    },
    {
      "id": 60,
      "Active": true,
      "VersionId": 732,
      "Latitude": "48.36090760",
      "Longitude": "30.46588180",
      "FullName": "АЗС №58 06:00 - 21:00",
      "ShortName": "",
      "Address": "Кіровоградська обл., Голованівський р-н, автошлях Ульянівка-Миколаїв, 17 км + 650 м (праворуч)",
      "Region": "Кіровоградська",
      "LastPriceUpdateDate": "2022-06-04",
      "ServicesAsArray": [
        {
          "id": 1,
          "Title": "Магазин"
        },
        {
          "id": 2,
          "Title": "WC"
        }
      ],
      "FuelsAsArray": [
        {
          "id": 2,
          "Title": "95 (передоплата)",
          "Price": "0.00"
        },
        {
          "id": 4,
          "Title": "Газ",
          "Price": "37.00"
        },
        {
          "id": 5,
          "Title": "ДП (передоплата)",
          "Price": "0.00"
        },
        {
          "id": 9,
          "Title": "upg 95",
          "Price": "49.00"
        }
      ]
    },
    {
      "id": 61,
      "Active": true,
      "VersionId": 734,
      "Latitude": "48.36090760",
      "Longitude": "30.46588180",
      "FullName": "АЗС №59 06:00 - 21:00",
      "ShortName": "",
      "Address": "Кіровоградська обл., Голованівський р-н, автошлях Ульянівка-Миколаїв, 17 км + 735 м (ліворуч)",
      "Region": "Кіровоградська",
      "LastPriceUpdateDate": "2022-06-04",
      "ServicesAsArray": [
        {
          "id": 1,
          "Title": "Магазин"
        },
        {
          "id": 2,
          "Title": "WC"
        }
      ],
      "FuelsAsArray": [
        {
          "id": 2,
          "Title": "95 (передоплата)",
          "Price": "0.00"
        },
        {
          "id": 3,
          "Title": "92 (передоплата)",
          "Price": "0.00"
        },
        {
          "id": 4,
          "Title": "Газ",
          "Price": "37.00"
        },
        {
          "id": 5,
          "Title": "ДП (передоплата)",
          "Price": "0.00"
        }
      ]
    },
    {
      "id": 77,
      "Active": true,
      "VersionId": 758,
      "Latitude": "49.06980000",
      "Longitude": "33.25050000",
      "FullName": "АЗС №70 05:00 - 22:00",
      "ShortName": "",
      "Address": "Кіровоградська обл., м. Свідловодськ, вул. Єгорова, 2А",
      "Region": "Кіровоградська",
      "LastPriceUpdateDate": "2022-06-04",
      "ServicesAsArray": [
        {
          "id": 1,
          "Title": "Магазин"
        },
        {
          "id": 2,
          "Title": "WC"
        }
      ],
      "FuelsAsArray": [
        {
          "id": 1,
          "Title": "upg DP",
          "Price": "0.00"
        },
        {
          "id": 2,
          "Title": "95 (передоплата)",
          "Price": "0.00"
        },
        {
          "id": 4,
          "Title": "Газ",
          "Price": "37.00"
        },
        {
          "id": 9,
          "Title": "upg 95",
          "Price": "0.00"
        }
      ]
    },
    {
      "id": 78,
      "Active": true,
      "VersionId": 760,
      "Latitude": "49.04925000",
      "Longitude": "33.19525000",
      "FullName": "АЗС№71 05:00 - 22:00",
      "ShortName": "",
      "Address": "Кіровоградська обл., м. Свідловодськ, вул. Миру, 127",
      "Region": "Кіровоградська",
      "LastPriceUpdateDate": "2022-06-04",
      "ServicesAsArray": [
        {
          "id": 1,
          "Title": "Магазин"
        },
        {
          "id": 2,
          "Title": "WC"
        }
      ],
      "FuelsAsArray": [
        {
          "id": 2,
          "Title": "95 (передоплата)",
          "Price": "0.00"
        },
        {
          "id": 4,
          "Title": "Газ",
          "Price": "37.00"
        },
        {
          "id": 5,
          "Title": "ДП (передоплата)",
          "Price": "0.00"
        },
        {
          "id": 9,
          "Title": "upg 95",
          "Price": "0.00"
        }
      ]
    },
    {
      "id": 79,
      "Active": true,
      "VersionId": 762,
      "Latitude": "48.92102000",
      "Longitude": "33.36103000",
      "FullName": "АЗС №72 06:00 - 22:00",
      "ShortName": "",
      "Address": "Кіровоградська обл., смт Павлиш, вул. Сухомлинського, 23А",
      "Region": "Кіровоградська",
      "LastPriceUpdateDate": "2022-06-04",
      "ServicesAsArray": [
        {
          "id": 1,
          "Title": "Магазин"
        },
        {
          "id": 2,
          "Title": "WC"
        }
      ],
      "FuelsAsArray": [
        {
          "id": 1,
          "Title": "upg DP",
          "Price": "0.00"
        },
        {
          "id": 2,
          "Title": "95 (передоплата)",
          "Price": "0.00"
        },
        {
          "id": 4,
          "Title": "Газ",
          "Price": "37.00"
        },
        {
          "id": 9,
          "Title": "upg 95",
          "Price": "0.00"
        }
      ]
    },
    {
      "id": 9,
      "Active": true,
      "VersionId": 696,
      "Latitude": "49.85918000",
      "Longitude": "23.97305000",
      "FullName": "АЗС  №5 05:00 - 23:00",
      "ShortName": "",
      "Address": "м. Львів, вул. Шевченка, 200",
      "Region": "Львівська",
      "LastPriceUpdateDate": "2022-06-04",
      "ServicesAsArray": [
        {
          "id": 1,
          "Title": "Магазин"
        },
        {
          "id": 2,
          "Title": "WC"
        },
        {
          "id": 6,
          "Title": "Термінал EasyPay"
        }
      ],
      "FuelsAsArray": [
        {
          "id": 2,
          "Title": "95 (передоплата)",
          "Price": "0.00"
        },
        {
          "id": 4,
          "Title": "Газ",
          "Price": "0.00"
        },
        {
          "id": 5,
          "Title": "ДП (передоплата)",
          "Price": "0.00"
        },
        {
          "id": 9,
          "Title": "upg 95",
          "Price": "49.00"
        }
      ]
    },
    {
      "id": 58,
      "Active": true,
      "VersionId": 728,
      "Latitude": "50.06562000",
      "Longitude": "25.15565000",
      "FullName": "АЗС №56 07:00 - 22:00",
      "ShortName": "",
      "Address": "Львівська обл., м. Броди, а/д Київ - Чоп 441 км + 500 м (праворуч)",
      "Region": "Львівська",
      "LastPriceUpdateDate": "2022-06-04",
      "ServicesAsArray": [
        {
          "id": 1,
          "Title": "Магазин"
        },
        {
          "id": 2,
          "Title": "WC"
        },
        {
          "id": 6,
          "Title": "Термінал EasyPay"
        }
      ],
      "FuelsAsArray": [
        {
          "id": 1,
          "Title": "upg DP",
          "Price": "0.00"
        },
        {
          "id": 2,
          "Title": "95 (передоплата)",
          "Price": "0.00"
        },
        {
          "id": 4,
          "Title": "Газ",
          "Price": "0.00"
        },
        {
          "id": 9,
          "Title": "upg 95",
          "Price": "0.00"
        }
      ]
    },
    {
      "id": 59,
      "Active": true,
      "VersionId": 730,
      "Latitude": "50.06637000",
      "Longitude": "25.15482000",
      "FullName": "АЗС №57 07:00 - 22:00",
      "ShortName": "",
      "Address": "Львівська обл., м. Броди, а/д Київ - Чоп 441 км + 470 м (ліворуч)",
      "Region": "Львівська",
      "LastPriceUpdateDate": "2022-06-04",
      "ServicesAsArray": [
        {
          "id": 1,
          "Title": "Магазин"
        },
        {
          "id": 2,
          "Title": "WC"
        },
        {
          "id": 6,
          "Title": "Термінал EasyPay"
        }
      ],
      "FuelsAsArray": [
        {
          "id": 2,
          "Title": "95 (передоплата)",
          "Price": "0.00"
        },
        {
          "id": 3,
          "Title": "92 (передоплата)",
          "Price": "0.00"
        },
        {
          "id": 4,
          "Title": "Газ",
          "Price": "0.00"
        },
        {
          "id": 5,
          "Title": "ДП (передоплата)",
          "Price": "0.00"
        }
      ]
    },
    {
      "id": 80,
      "Active": true,
      "VersionId": 764,
      "Latitude": "49.81773000",
      "Longitude": "24.16147000",
      "FullName": "АЗС №4 05:00 - 23:00",
      "ShortName": "",
      "Address": "Львівська обл., Пустомитівський р-н,  с. Підберізці, вул. Галицька, 1",
      "Region": "Львівська",
      "LastPriceUpdateDate": "2022-06-04",
      "ServicesAsArray": [
        {
          "id": 1,
          "Title": "Магазин"
        },
        {
          "id": 2,
          "Title": "WC"
        },
        {
          "id": 5,
          "Title": "Кава"
        }
      ],
      "FuelsAsArray": [
        {
          "id": 1,
          "Title": "upg DP",
          "Price": "0.00"
        },
        {
          "id": 2,
          "Title": "95 (передоплата)",
          "Price": "48.90"
        },
        {
          "id": 4,
          "Title": "Газ",
          "Price": "37.00"
        },
        {
          "id": 5,
          "Title": "ДП (передоплата)",
          "Price": "0.00"
        },
        {
          "id": 9,
          "Title": "upg 95",
          "Price": "0.00"
        }
      ]
    },
    {
      "id": 115,
      "Active": true,
      "VersionId": 816,
      "Latitude": "49.74642200",
      "Longitude": "24.01473200",
      "FullName": "АЗС №95 05:00 - 23:00",
      "ShortName": "",
      "Address": "Львівська обл., Пустомитівський р-н, с. Солонка, вул. Стрийська, 3",
      "Region": "Львівська",
      "LastPriceUpdateDate": "2022-06-04",
      "ServicesAsArray": [
        {
          "id": 1,
          "Title": "Магазин"
        },
        {
          "id": 2,
          "Title": "WC"
        },
        {
          "id": 3,
          "Title": "Wi-Fi"
        },
        {
          "id": 4,
          "Title": "Їжа"
        },
        {
          "id": 5,
          "Title": "Кава"
        },
        {
          "id": 6,
          "Title": "Термінал EasyPay"
        },
        {
          "id": 8,
          "Title": "Підкачка шин"
        },
        {
          "id": 10,
          "Title": "VIVO-cafe"
        }
      ],
      "FuelsAsArray": [
        {
          "id": 1,
          "Title": "upg DP",
          "Price": "0.00"
        },
        {
          "id": 2,
          "Title": "95 (передоплата)",
          "Price": "0.00"
        },
        {
          "id": 5,
          "Title": "ДП (передоплата)",
          "Price": "0.00"
        },
        {
          "id": 9,
          "Title": "upg 95",
          "Price": "0.00"
        }
      ]
    },
    {
      "id": 125,
      "Active": true,
      "VersionId": 836,
      "Latitude": "49.77136000",
      "Longitude": "24.10245200",
      "FullName": "АЗС №100 05:00 - 23:00",
      "ShortName": "",
      "Address": "Львівська обл., Пустомитівський р-н, с. Пасіки-Зубрицькі, вул. Дорожна, 85",
      "Region": "Львівська",
      "LastPriceUpdateDate": "2022-06-04",
      "ServicesAsArray": [
        {
          "id": 1,
          "Title": "Магазин"
        },
        {
          "id": 2,
          "Title": "WC"
        },
        {
          "id": 3,
          "Title": "Wi-Fi"
        },
        {
          "id": 4,
          "Title": "Їжа"
        },
        {
          "id": 5,
          "Title": "Кава"
        },
        {
          "id": 6,
          "Title": "Термінал EasyPay"
        },
        {
          "id": 8,
          "Title": "Підкачка шин"
        }
      ],
      "FuelsAsArray": [
        {
          "id": 1,
          "Title": "upg DP",
          "Price": "0.00"
        },
        {
          "id": 2,
          "Title": "95 (передоплата)",
          "Price": "0.00"
        },
        {
          "id": 4,
          "Title": "Газ",
          "Price": "0.00"
        },
        {
          "id": 5,
          "Title": "ДП (передоплата)",
          "Price": "0.00"
        },
        {
          "id": 9,
          "Title": "upg 95",
          "Price": "0.00"
        }
      ]
    },
    {
      "id": 133,
      "Active": true,
      "VersionId": 852,
      "Latitude": "49.76736900",
      "Longitude": "24.08921900",
      "FullName": "АЗС №108 05:00 - 23:00",
      "ShortName": "",
      "Address": "Львівська обл., Пустомитівський р-н, с. Пасіки-Зубрицькі, вул. Кільцева, 6",
      "Region": "Львівська",
      "LastPriceUpdateDate": "2022-06-04",
      "ServicesAsArray": [
        {
          "id": 1,
          "Title": "Магазин"
        },
        {
          "id": 2,
          "Title": "WC"
        },
        {
          "id": 3,
          "Title": "Wi-Fi"
        },
        {
          "id": 4,
          "Title": "Їжа"
        },
        {
          "id": 5,
          "Title": "Кава"
        },
        {
          "id": 6,
          "Title": "Термінал EasyPay"
        },
        {
          "id": 8,
          "Title": "Підкачка шин"
        },
        {
          "id": 10,
          "Title": "VIVO-cafe"
        }
      ],
      "FuelsAsArray": [
        {
          "id": 1,
          "Title": "upg DP",
          "Price": "0.00"
        },
        {
          "id": 2,
          "Title": "95 (передоплата)",
          "Price": "0.00"
        },
        {
          "id": 4,
          "Title": "Газ",
          "Price": "37.00"
        },
        {
          "id": 5,
          "Title": "ДП (передоплата)",
          "Price": "0.00"
        },
        {
          "id": 9,
          "Title": "upg 95",
          "Price": "49.00"
        }
      ]
    },
    {
      "id": 87,
      "Active": true,
      "VersionId": 680,
      "Latitude": "46.47933600",
      "Longitude": "30.61596600",
      "FullName": "АЗС №81 06:00 - 21:00",
      "ShortName": "",
      "Address": "Одеська обл., Овідіопольский р-н, смт Авангард, вул. Ангарська, 4",
      "Region": "Одеська",
      "LastPriceUpdateDate": "2022-06-04",
      "ServicesAsArray": [
        {
          "id": 1,
          "Title": "Магазин"
        },
        {
          "id": 2,
          "Title": "WC"
        }
      ],
      "FuelsAsArray": [
        {
          "id": 1,
          "Title": "upg DP",
          "Price": "0.00"
        },
        {
          "id": 2,
          "Title": "95 (передоплата)",
          "Price": "0.00"
        },
        {
          "id": 4,
          "Title": "Газ",
          "Price": "0.00"
        },
        {
          "id": 5,
          "Title": "ДП (передоплата)",
          "Price": "0.00"
        },
        {
          "id": 9,
          "Title": "upg 95",
          "Price": "0.00"
        }
      ]
    },
    {
      "id": 99,
      "Active": true,
      "VersionId": 788,
      "Latitude": "46.45253000",
      "Longitude": "30.72935000",
      "FullName": "АЗС №88 06:00 - 21:00",
      "ShortName": "",
      "Address": "м. Одеса, вул. Люстдорфська дорога, 5",
      "Region": "Одеська",
      "LastPriceUpdateDate": "2022-06-04",
      "ServicesAsArray": [
        {
          "id": 1,
          "Title": "Магазин"
        },
        {
          "id": 2,
          "Title": "WC"
        }
      ],
      "FuelsAsArray": [
        {
          "id": 2,
          "Title": "95 (передоплата)",
          "Price": "0.00"
        },
        {
          "id": 5,
          "Title": "ДП (передоплата)",
          "Price": "0.00"
        },
        {
          "id": 9,
          "Title": "upg 95",
          "Price": "0.00"
        }
      ]
    },
    {
      "id": 136,
      "Active": true,
      "VersionId": 862,
      "Latitude": "46.55798800",
      "Longitude": "30.58490700",
      "FullName": "АЗС №111 06:00 - 21:00",
      "ShortName": "",
      "Address": "Одеська обл., Біляївський р-н, Нерубайська с/р, Масив 27, зем. діл. 306-а, вздовж а/д М05 Київ-Одеса",
      "Region": "Одеська",
      "LastPriceUpdateDate": "2022-06-04",
      "ServicesAsArray": [
        {
          "id": 1,
          "Title": "Магазин"
        },
        {
          "id": 2,
          "Title": "WC"
        },
        {
          "id": 3,
          "Title": "Wi-Fi"
        },
        {
          "id": 4,
          "Title": "Їжа"
        },
        {
          "id": 5,
          "Title": "Кава"
        },
        {
          "id": 8,
          "Title": "Підкачка шин"
        },
        {
          "id": 10,
          "Title": "VIVO-cafe"
        }
      ],
      "FuelsAsArray": [
        {
          "id": 1,
          "Title": "upg DP",
          "Price": "0.00"
        },
        {
          "id": 2,
          "Title": "95 (передоплата)",
          "Price": "0.00"
        },
        {
          "id": 4,
          "Title": "Газ",
          "Price": "0.00"
        },
        {
          "id": 5,
          "Title": "ДП (передоплата)",
          "Price": "0.00"
        },
        {
          "id": 9,
          "Title": "upg 95",
          "Price": "0.00"
        }
      ]
    },
    {
      "id": 140,
      "Active": true,
      "VersionId": 982,
      "Latitude": "46.52908000",
      "Longitude": "30.72993000",
      "FullName": "АЗС №114 06:00 - 21:00",
      "ShortName": "",
      "Address": "Одеська обл., м. Одеса,  вул. Головатого отамана, 157-А",
      "Region": "Одеська",
      "LastPriceUpdateDate": "2022-06-04",
      "ServicesAsArray": [
        {
          "id": 1,
          "Title": "Магазин"
        },
        {
          "id": 2,
          "Title": "WC"
        },
        {
          "id": 3,
          "Title": "Wi-Fi"
        },
        {
          "id": 4,
          "Title": "Їжа"
        },
        {
          "id": 5,
          "Title": "Кава"
        },
        {
          "id": 8,
          "Title": "Підкачка шин"
        },
        {
          "id": 10,
          "Title": "VIVO-cafe"
        }
      ],
      "FuelsAsArray": [
        {
          "id": 1,
          "Title": "upg DP",
          "Price": "0.00"
        },
        {
          "id": 2,
          "Title": "95 (передоплата)",
          "Price": "0.00"
        },
        {
          "id": 4,
          "Title": "Газ",
          "Price": "0.00"
        },
        {
          "id": 5,
          "Title": "ДП (передоплата)",
          "Price": "0.00"
        },
        {
          "id": 9,
          "Title": "upg 95",
          "Price": "0.00"
        }
      ]
    },
    {
      "id": 153,
      "Active": true,
      "VersionId": 964,
      "Latitude": "46.47919000",
      "Longitude": "30.61719600",
      "FullName": "АЗС №127 05:00 - 21:30",
      "ShortName": "",
      "Address": "Одеська обл., м. Одеса, Малиновський р-н, масив №1, ділянка №13",
      "Region": "Одеська",
      "LastPriceUpdateDate": "2022-06-04",
      "ServicesAsArray": [
        {
          "id": 1,
          "Title": "Магазин"
        },
        {
          "id": 2,
          "Title": "WC"
        },
        {
          "id": 3,
          "Title": "Wi-Fi"
        },
        {
          "id": 4,
          "Title": "Їжа"
        },
        {
          "id": 5,
          "Title": "Кава"
        },
        {
          "id": 6,
          "Title": "Термінал EasyPay"
        },
        {
          "id": 8,
          "Title": "Підкачка шин"
        },
        {
          "id": 10,
          "Title": "VIVO-cafe"
        }
      ],
      "FuelsAsArray": [
        {
          "id": 1,
          "Title": "upg DP",
          "Price": "0.00"
        },
        {
          "id": 2,
          "Title": "95 (передоплата)",
          "Price": "0.00"
        },
        {
          "id": 4,
          "Title": "Газ",
          "Price": "37.00"
        },
        {
          "id": 5,
          "Title": "ДП (передоплата)",
          "Price": "0.00"
        },
        {
          "id": 9,
          "Title": "upg 95",
          "Price": "0.00"
        }
      ]
    },
    {
      "id": 152,
      "Active": true,
      "VersionId": 956,
      "Latitude": "49.10056000",
      "Longitude": "33.41831000",
      "FullName": "АЗС №126 05:00 - 22:00",
      "ShortName": "",
      "Address": "Полтавська обл., м. Кременчук, вул. Київська, в районі автосалону «АИС»",
      "Region": "Полтавська",
      "LastPriceUpdateDate": "2022-06-04",
      "ServicesAsArray": [
        {
          "id": 1,
          "Title": "Магазин"
        },
        {
          "id": 2,
          "Title": "WC"
        },
        {
          "id": 3,
          "Title": "Wi-Fi"
        },
        {
          "id": 4,
          "Title": "Їжа"
        },
        {
          "id": 5,
          "Title": "Кава"
        },
        {
          "id": 6,
          "Title": "Термінал EasyPay"
        },
        {
          "id": 8,
          "Title": "Підкачка шин"
        },
        {
          "id": 10,
          "Title": "VIVO-cafe"
        }
      ],
      "FuelsAsArray": [
        {
          "id": 1,
          "Title": "upg DP",
          "Price": "0.00"
        },
        {
          "id": 2,
          "Title": "95 (передоплата)",
          "Price": "0.00"
        },
        {
          "id": 4,
          "Title": "Газ",
          "Price": "37.00"
        },
        {
          "id": 5,
          "Title": "ДП (передоплата)",
          "Price": "0.00"
        },
        {
          "id": 9,
          "Title": "upg 95",
          "Price": "0.00"
        }
      ]
    },
    {
      "id": 7,
      "Active": true,
      "VersionId": 692,
      "Latitude": "51.20447000",
      "Longitude": "27.29230000",
      "FullName": "АЗС №2 06:00 - 22:00",
      "ShortName": "",
      "Address": "Рівненська  обл., Рокитнівський р-н, с/рада Кисорицька, автодорога Київ-Ковель, 254 км",
      "Region": "Рівненська",
      "LastPriceUpdateDate": "2022-06-04",
      "ServicesAsArray": [
        {
          "id": 1,
          "Title": "Магазин"
        },
        {
          "id": 2,
          "Title": "WC"
        }
      ],
      "FuelsAsArray": [
        {
          "id": 1,
          "Title": "upg DP",
          "Price": "0.00"
        },
        {
          "id": 2,
          "Title": "95 (передоплата)",
          "Price": "0.00"
        },
        {
          "id": 4,
          "Title": "Газ",
          "Price": "0.00"
        },
        {
          "id": 9,
          "Title": "upg 95",
          "Price": "0.00"
        }
      ]
    },
    {
      "id": 132,
      "Active": true,
      "VersionId": 850,
      "Latitude": "50.63789400",
      "Longitude": "26.19568900",
      "FullName": "АЗС №107 05:00 - 23:00",
      "ShortName": "",
      "Address": "Рівненська обл., Рівненський р-н, с/рада Шпанівська, комплекс будівель і споруд №8, буд. 8",
      "Region": "Рівненська",
      "LastPriceUpdateDate": "2022-06-04",
      "ServicesAsArray": [
        {
          "id": 1,
          "Title": "Магазин"
        },
        {
          "id": 2,
          "Title": "WC"
        },
        {
          "id": 3,
          "Title": "Wi-Fi"
        },
        {
          "id": 4,
          "Title": "Їжа"
        },
        {
          "id": 5,
          "Title": "Кава"
        },
        {
          "id": 6,
          "Title": "Термінал EasyPay"
        },
        {
          "id": 8,
          "Title": "Підкачка шин"
        },
        {
          "id": 10,
          "Title": "VIVO-cafe"
        }
      ],
      "FuelsAsArray": [
        {
          "id": 1,
          "Title": "upg DP",
          "Price": "0.00"
        },
        {
          "id": 2,
          "Title": "95 (передоплата)",
          "Price": "0.00"
        },
        {
          "id": 4,
          "Title": "Газ",
          "Price": "0.00"
        },
        {
          "id": 5,
          "Title": "ДП (передоплата)",
          "Price": "0.00"
        },
        {
          "id": 9,
          "Title": "upg 95",
          "Price": "49.00"
        }
      ]
    },
    {
      "id": 138,
      "Active": true,
      "VersionId": 870,
      "Latitude": "50.57247000",
      "Longitude": "26.28021000",
      "FullName": "АЗС №113 05:00 - 23:00",
      "ShortName": "",
      "Address": "Рівненська обл., Рівненський р-н, с. Корнин, вул. Об'їзна, 4",
      "Region": "Рівненська",
      "LastPriceUpdateDate": "2022-06-04",
      "ServicesAsArray": [
        {
          "id": 1,
          "Title": "Магазин"
        },
        {
          "id": 2,
          "Title": "WC"
        },
        {
          "id": 3,
          "Title": "Wi-Fi"
        },
        {
          "id": 4,
          "Title": "Їжа"
        },
        {
          "id": 5,
          "Title": "Кава"
        },
        {
          "id": 8,
          "Title": "Підкачка шин"
        },
        {
          "id": 10,
          "Title": "VIVO-cafe"
        }
      ],
      "FuelsAsArray": [
        {
          "id": 1,
          "Title": "upg DP",
          "Price": "0.00"
        },
        {
          "id": 2,
          "Title": "95 (передоплата)",
          "Price": "0.00"
        },
        {
          "id": 4,
          "Title": "Газ",
          "Price": "0.00"
        },
        {
          "id": 5,
          "Title": "ДП (передоплата)",
          "Price": "0.00"
        },
        {
          "id": 9,
          "Title": "upg 95",
          "Price": "0.00"
        }
      ]
    },
    {
      "id": 16,
      "Active": true,
      "VersionId": 708,
      "Latitude": "51.66605000",
      "Longitude": "33.91385000",
      "FullName": "АЗС №16 05:00 - 22:00",
      "ShortName": "",
      "Address": "Сумська обл., м. Глухів, вул. Путивльська, 62А",
      "Region": "Сумська",
      "LastPriceUpdateDate": "2022-06-04",
      "ServicesAsArray": [
        {
          "id": 1,
          "Title": "Магазин"
        },
        {
          "id": 2,
          "Title": "WC"
        },
        {
          "id": 6,
          "Title": "Термінал EasyPay"
        }
      ],
      "FuelsAsArray": [
        {
          "id": 1,
          "Title": "upg DP",
          "Price": "0.00"
        },
        {
          "id": 2,
          "Title": "95 (передоплата)",
          "Price": "0.00"
        },
        {
          "id": 5,
          "Title": "ДП (передоплата)",
          "Price": "0.00"
        },
        {
          "id": 9,
          "Title": "upg 95",
          "Price": "0.00"
        }
      ]
    },
    {
      "id": 154,
      "Active": true,
      "VersionId": 962,
      "Latitude": "49.52601200",
      "Longitude": "25.60574500",
      "FullName": "АЗС №128 05:00 - 22:00",
      "ShortName": "",
      "Address": "Тернопільська обл., Тернгопільський р-н, с. Великі Гаї, вул. Об'їзна, 33",
      "Region": "Тернопільська",
      "LastPriceUpdateDate": "2022-06-04",
      "ServicesAsArray": [
        {
          "id": 1,
          "Title": "Магазин"
        },
        {
          "id": 2,
          "Title": "WC"
        },
        {
          "id": 3,
          "Title": "Wi-Fi"
        },
        {
          "id": 4,
          "Title": "Їжа"
        },
        {
          "id": 5,
          "Title": "Кава"
        },
        {
          "id": 6,
          "Title": "Термінал EasyPay"
        },
        {
          "id": 8,
          "Title": "Підкачка шин"
        },
        {
          "id": 10,
          "Title": "VIVO-cafe"
        }
      ],
      "FuelsAsArray": [
        {
          "id": 1,
          "Title": "upg DP",
          "Price": "0.00"
        },
        {
          "id": 2,
          "Title": "95 (передоплата)",
          "Price": "0.00"
        },
        {
          "id": 4,
          "Title": "Газ",
          "Price": "0.00"
        },
        {
          "id": 5,
          "Title": "ДП (передоплата)",
          "Price": "0.00"
        },
        {
          "id": 9,
          "Title": "upg 95",
          "Price": "0.00"
        }
      ]
    },
    {
      "id": 137,
      "Active": false,
      "VersionId": 858,
      "Latitude": "49.98526400",
      "Longitude": "36.27849600",
      "FullName": "АЗС №112",
      "ShortName": "",
      "Address": "Харківська обл., м. Харків, вул. Академіка Павлова, 18-Б",
      "Region": "Харківська",
      "LastPriceUpdateDate": "2022-06-04",
      "ServicesAsArray": [
        {
          "id": 1,
          "Title": "Магазин"
        },
        {
          "id": 2,
          "Title": "WC"
        },
        {
          "id": 3,
          "Title": "Wi-Fi"
        },
        {
          "id": 4,
          "Title": "Їжа"
        },
        {
          "id": 5,
          "Title": "Кава"
        },
        {
          "id": 6,
          "Title": "Термінал EasyPay"
        },
        {
          "id": 8,
          "Title": "Підкачка шин"
        },
        {
          "id": 10,
          "Title": "VIVO-cafe"
        }
      ],
      "FuelsAsArray": [
        {
          "id": 2,
          "Title": "95 (передоплата)",
          "Price": "48.90"
        },
        {
          "id": 3,
          "Title": "92 (передоплата)",
          "Price": "48.90"
        },
        {
          "id": 4,
          "Title": "Газ",
          "Price": "34.00"
        },
        {
          "id": 5,
          "Title": "ДП (передоплата)",
          "Price": "51.00"
        },
        {
          "id": 8,
          "Title": "upg 100",
          "Price": "49.50"
        }
      ]
    },
    {
      "id": 129,
      "Active": true,
      "VersionId": 844,
      "Latitude": "48.70669300",
      "Longitude": "26.58985700",
      "FullName": "АЗС №105 05:00 - 23:00",
      "ShortName": "",
      "Address": "Хмельницька обл., м. Кам'янець-Подільський, Хмельницьке шосе, 11В",
      "Region": "Хмельницька",
      "LastPriceUpdateDate": "2022-06-04",
      "ServicesAsArray": [
        {
          "id": 1,
          "Title": "Магазин"
        },
        {
          "id": 2,
          "Title": "WC"
        },
        {
          "id": 3,
          "Title": "Wi-Fi"
        },
        {
          "id": 4,
          "Title": "Їжа"
        },
        {
          "id": 5,
          "Title": "Кава"
        },
        {
          "id": 6,
          "Title": "Термінал EasyPay"
        },
        {
          "id": 8,
          "Title": "Підкачка шин"
        },
        {
          "id": 10,
          "Title": "VIVO-cafe"
        }
      ],
      "FuelsAsArray": [
        {
          "id": 1,
          "Title": "upg DP",
          "Price": "0.00"
        },
        {
          "id": 2,
          "Title": "95 (передоплата)",
          "Price": "0.00"
        },
        {
          "id": 4,
          "Title": "Газ",
          "Price": "0.00"
        },
        {
          "id": 5,
          "Title": "ДП (передоплата)",
          "Price": "0.00"
        },
        {
          "id": 9,
          "Title": "upg 95",
          "Price": "0.00"
        }
      ]
    },
    {
      "id": 83,
      "Active": true,
      "VersionId": 672,
      "Latitude": "48.74775000",
      "Longitude": "30.19140000",
      "FullName": "АЗС №78 06:00 - 21:00",
      "ShortName": "",
      "Address": "Черкаська обл., м. Умань, вул. Заводська, 1А",
      "Region": "Черкаська",
      "LastPriceUpdateDate": "2022-06-04",
      "ServicesAsArray": [
        {
          "id": 1,
          "Title": "Магазин"
        },
        {
          "id": 2,
          "Title": "WC"
        },
        {
          "id": 6,
          "Title": "Термінал EasyPay"
        },
        {
          "id": 7,
          "Title": "СТО"
        }
      ],
      "FuelsAsArray": [
        {
          "id": 2,
          "Title": "95 (передоплата)",
          "Price": "0.00"
        },
        {
          "id": 5,
          "Title": "ДП (передоплата)",
          "Price": "0.00"
        },
        {
          "id": 9,
          "Title": "upg 95",
          "Price": "49.00"
        }
      ]
    },
    {
      "id": 148,
      "Active": true,
      "VersionId": 920,
      "Latitude": "49.42134200",
      "Longitude": "32.01761900",
      "FullName": "АЗС №122 05:00 - 23:00",
      "ShortName": "",
      "Address": "м. Черкаси, вул. 30-річчя Перемоги, 13/7",
      "Region": "Черкаська",
      "LastPriceUpdateDate": "2022-06-04",
      "ServicesAsArray": [
        {
          "id": 1,
          "Title": "Магазин"
        },
        {
          "id": 2,
          "Title": "WC"
        },
        {
          "id": 3,
          "Title": "Wi-Fi"
        },
        {
          "id": 4,
          "Title": "Їжа"
        },
        {
          "id": 5,
          "Title": "Кава"
        },
        {
          "id": 6,
          "Title": "Термінал EasyPay"
        },
        {
          "id": 8,
          "Title": "Підкачка шин"
        },
        {
          "id": 10,
          "Title": "VIVO-cafe"
        }
      ],
      "FuelsAsArray": [
        {
          "id": 1,
          "Title": "upg DP",
          "Price": "0.00"
        },
        {
          "id": 2,
          "Title": "95 (передоплата)",
          "Price": "0.00"
        },
        {
          "id": 4,
          "Title": "Газ",
          "Price": "0.00"
        },
        {
          "id": 5,
          "Title": "ДП (передоплата)",
          "Price": "0.00"
        },
        {
          "id": 9,
          "Title": "upg 95",
          "Price": "49.00"
        }
      ]
    },
    {
      "id": 151,
      "Active": true,
      "VersionId": 974,
      "Latitude": "48.55082500",
      "Longitude": "30.23045300",
      "FullName": "АЗС №125 05:00 - 22:00",
      "ShortName": "",
      "Address": "Черкаська обл., Ладижинська сільська рада, с. Ладижинка, вул.Київська, 35",
      "Region": "Черкаська",
      "LastPriceUpdateDate": "2022-06-04",
      "ServicesAsArray": [
        {
          "id": 1,
          "Title": "Магазин"
        },
        {
          "id": 2,
          "Title": "WC"
        },
        {
          "id": 3,
          "Title": "Wi-Fi"
        },
        {
          "id": 4,
          "Title": "Їжа"
        },
        {
          "id": 5,
          "Title": "Кава"
        },
        {
          "id": 6,
          "Title": "Термінал EasyPay"
        },
        {
          "id": 8,
          "Title": "Підкачка шин"
        },
        {
          "id": 10,
          "Title": "VIVO-cafe"
        }
      ],
      "FuelsAsArray": [
        {
          "id": 1,
          "Title": "upg DP",
          "Price": "0.00"
        },
        {
          "id": 2,
          "Title": "95 (передоплата)",
          "Price": "0.00"
        },
        {
          "id": 4,
          "Title": "Газ",
          "Price": "37.00"
        },
        {
          "id": 5,
          "Title": "ДП (передоплата)",
          "Price": "0.00"
        },
        {
          "id": 9,
          "Title": "upg 95",
          "Price": "49.00"
        }
      ]
    },
    {
      "id": 126,
      "Active": true,
      "VersionId": 838,
      "Latitude": "47.99862300",
      "Longitude": "26.05029400",
      "FullName": "АЗС №103 06:00 - 22:00",
      "ShortName": "",
      "Address": "Чернівецька обл., Глибоцький р-н, с. Тереблече, вул. Головна, 139В",
      "Region": "Чернівецька",
      "LastPriceUpdateDate": "2022-06-04",
      "ServicesAsArray": [
        {
          "id": 1,
          "Title": "Магазин"
        },
        {
          "id": 2,
          "Title": "WC"
        },
        {
          "id": 3,
          "Title": "Wi-Fi"
        },
        {
          "id": 4,
          "Title": "Їжа"
        },
        {
          "id": 5,
          "Title": "Кава"
        },
        {
          "id": 6,
          "Title": "Термінал EasyPay"
        },
        {
          "id": 8,
          "Title": "Підкачка шин"
        },
        {
          "id": 10,
          "Title": "VIVO-cafe"
        }
      ],
      "FuelsAsArray": [
        {
          "id": 2,
          "Title": "95 (передоплата)",
          "Price": "0.00"
        },
        {
          "id": 4,
          "Title": "Газ",
          "Price": "37.00"
        },
        {
          "id": 5,
          "Title": "ДП (передоплата)",
          "Price": "0.00"
        },
        {
          "id": 9,
          "Title": "upg 95",
          "Price": "49.00"
        }
      ]
    }
  ],
  "update": []
}